MANIFEST.in
README.md
setup.py
strakspos/__init__.py
strakspos/minipos.py
strakspos/sendmail.py
strakspos/stak.py
strakspos/strakspos.cfg.sample
strakspos.egg-info/PKG-INFO
strakspos.egg-info/SOURCES.txt
strakspos.egg-info/dependency_links.txt
strakspos.egg-info/entry_points.txt
strakspos.egg-info/not-zip-safe
strakspos.egg-info/requires.txt
strakspos.egg-info/top_level.txt
strakspos/assets/FontAwesome.otf
strakspos/assets/bg.jpg
strakspos/assets/bootstrap-reset.css
strakspos/assets/bootstrap.js
strakspos/assets/bootstrap.min.css
strakspos/assets/favicon.png
strakspos/assets/font-awesome.css
strakspos/assets/fontawesome-webfont.eot
strakspos/assets/fontawesome-webfont.svg
strakspos/assets/fontawesome-webfont.ttf
strakspos/assets/fontawesome-webfont.woff
strakspos/assets/framework.css
strakspos/assets/fullogo.png
strakspos/assets/jquery.base.js
strakspos/assets/jquery.dcjqaccordion.2.7.js
strakspos/assets/jquery.js
strakspos/assets/repo_logo.png
strakspos/assets/reset-responsive.css
strakspos/assets/scripts.js
strakspos/assets/straks-icon.png
strakspos/assets/straks-logo.png
strakspos/assets/straks.png
strakspos/assets/swal.js
strakspos/assets/sweetalert.min.js
strakspos/resources/error.html
strakspos/resources/invoice.html
strakspos/resources/log_footer.html
strakspos/resources/log_header.html
strakspos/resources/logs.html
strakspos/resources/noaddrs.html
strakspos/resources/request.html
strakspos/resources/timeout.html
strakspos/resources/welcome.html
strakspos/resources/welcome_footer.html