Metadata-Version: 1.1
Name: strakspos
Version: 1.0.3
Summary: STRAKS POS
Home-page: https://straks.tech
Author: Freeman
Author-email: freeman@straks.tech
License: Apache
Keywords: STRAKS STAK POS minipos
Platform: UNKNOWN
Classifier: Programming Language :: Python :: 3
Classifier: Programming Language :: Python :: 3.2
Classifier: Programming Language :: Python :: 3.3
Classifier: Programming Language :: Python :: 3.4
Classifier: Programming Language :: Python :: 3.6
